intake_forecast/__init__.py
intake_forecast/functions.py
intake_forecast/source.py
intake_forecast/utils.py
intake_forecast-0.3.1.dist-info/licenses/AUTHORS.rst
intake_forecast-0.3.1.dist-info/METADATA
intake_forecast-0.3.1.dist-info/WHEEL
intake_forecast-0.3.1.dist-info/entry_points.txt
intake_forecast-0.3.1.dist-info/top_level.txt
intake_forecast-0.3.1.dist-info/RECORD
